LICENSE
MANIFEST.in
README.md
requirements.txt
setup.py
test-requirements.txt
datacanvas/__init__.py
datacanvas/clusters.py
datacanvas/ehc_client.py
datacanvas/io_types.py
datacanvas/log_parser.py
datacanvas/module.py
datacanvas/new_runtime.py
datacanvas/runtime.py
datacanvas/utils.py
datacanvas/validate.py
datacanvas/version.py
py3DataCanvas.egg-info/PKG-INFO
py3DataCanvas.egg-info/SOURCES.txt
py3DataCanvas.egg-info/dependency_links.txt
py3DataCanvas.egg-info/not-zip-safe
py3DataCanvas.egg-info/requires.txt
py3DataCanvas.egg-info/top_level.txt